hallon/__init__.py
hallon/ap.py
hallon/cli.py
hallon/exception.py
hallon/func.py
hallon/lang.py
hallon/switch.py
hallon/tools.py
hallon/topo.py
hallon-0.0.2.dist-info/LICENSE
hallon-0.0.2.dist-info/METADATA
hallon-0.0.2.dist-info/WHEEL
hallon-0.0.2.dist-info/entry_points.txt
hallon-0.0.2.dist-info/top_level.txt
hallon-0.0.2.dist-info/RECORD
