Metadata-Version: 2.1
Name: hallon
Version: 0.0.2
Summary: hallon is a package for network debugging
Home-page: https://github.com/RyanYuanSun/hallon
Author: Ryan Alloriadonis
Author-email: yuantai78@gmail.com
License: MIT License
Requires-Python: >=3.7
License-File: LICENSE
